[{"key":"fr","value":"1jbew1uFcFx8cDIzO.AWUT6_WikXKh4zJlWxSBRyFwcZk.BcF0DV.Zy.AAA.0.0.BcF0DW.AWW3I3qr","expires":"2019-03-17T06:23:18.000Z","maxAge":7776000,"domain":"facebook.com","path":"/","secure":true,"httpOnly":true,"hostOnly":false,"creation":"2018-12-17T06:23:18.037Z","lastAccessed":"2018-12-17T06:23:23.624Z"},{"key":"sb","value":"1UAXXNo4j8DpHqfowQEyXZ4S","expires":"2020-12-16T06:23:18.000Z","maxAge":63072000,"domain":"facebook.com","path":"/","secure":true,"httpOnly":true,"hostOnly":false,"creation":"2018-12-17T06:23:18.038Z","lastAccessed":"2018-12-17T06:23:23.624Z"},{"key":"datr","value":"1UAXXCZB_It3PupVl-oX5fwL","domain":"facebook.com","path":"/","hostOnly":false,"creation":"2018-12-17T06:23:18.108Z","lastAccessed":"2018-12-17T06:23:23.624Z"},{"key":"c_user","value":"100024954724825","expires":"2019-03-17T06:23:18.000Z","maxAge":7776000,"domain":"facebook.com","path":"/","secure":true,"hostOnly":false,"creation":"2018-12-17T06:23:18.824Z","lastAccessed":"2018-12-17T06:23:23.624Z"},{"key":"xs","value":"12%3AREy7ahPzntOnYQ%3A2%3A1545027798%3A14328%3A2627","expires":"2019-03-17T06:23:18.000Z","maxAge":7776000,"domain":"facebook.com","path":"/","secure":true,"httpOnly":true,"hostOnly":false,"creation":"2018-12-17T06:23:18.824Z","lastAccessed":"2018-12-17T06:23:23.624Z"},{"key":"pl","value":"n","expires":"2019-03-17T06:23:18.000Z","maxAge":7776000,"domain":"facebook.com","path":"/","secure":true,"httpOnly":true,"hostOnly":false,"creation":"2018-12-17T06:23:18.824Z","lastAccessed":"2018-12-17T06:23:23.624Z"},{"key":"spin","value":"r.4641669_b.trunk_t.1545027798_s.1_v.2_","expires":"2018-12-18T07:23:18.000Z","maxAge":90000,"domain":"facebook.com","path":"/","secure":true,"httpOnly":true,"hostOnly":false,"creation":"2018-12-17T06:23:18.914Z","lastAccessed":"2018-12-17T06:23:23.624Z"},{"key":"presence","value":"EDvF3EtimeF1545027803EuserFA21B24954724825A2EstateFDutF0Et2F_5b_5dElm2FnullEuct2F1545027803243EtrFnullEtwF710764223EatF1545027803243CEchFDp_5f1B24954724825F0CC","domain":"facebook.com","path":"/","secure":true,"hostOnly":false,"creation":"2018-12-17T06:23:23.244Z","lastAccessed":"2018-12-17T06:23:23.624Z"},{"key":"locale","value":"en_US","domain":"facebook.com","path":"/","secure":true,"hostOnly":false,"creation":"2018-12-17T06:23:23.245Z","lastAccessed":"2018-12-17T06:23:23.624Z"},{"key":"a11y","value":"%7B%22sr%22%3A0%2C%22sr-ts%22%3A1545027803245%2C%22jk%22%3A0%2C%22jk-ts%22%3A1545027803245%2C%22kb%22%3A0%2C%22kb-ts%22%3A1545027803245%2C%22hcm%22%3A0%2C%22hcm-ts%22%3A1545027803245%7D","domain":"facebook.com","path":"/","secure":true,"hostOnly":false,"creation":"2018-12-17T06:23:23.245Z","lastAccessed":"2018-12-17T06:23:23.624Z"},{"key":"fr","value":"1jbew1uFcFx8cDIzO.AWUT6_WikXKh4zJlWxSBRyFwcZk.BcF0DV.Zy.AAA.0.0.BcF0DW.AWW3I3qr","expires":"2019-03-17T06:23:18.000Z","maxAge":7776000,"domain":"facebook.com","path":"/","secure":true,"httpOnly":true,"hostOnly":false,"creation":"2018-12-17T06:23:18.037Z","lastAccessed":"2018-12-17T06:23:23.624Z"},{"key":"sb","value":"1UAXXNo4j8DpHqfowQEyXZ4S","expires":"2020-12-16T06:23:18.000Z","maxAge":63072000,"domain":"facebook.com","path":"/","secure":true,"httpOnly":true,"hostOnly":false,"creation":"2018-12-17T06:23:18.038Z","lastAccessed":"2018-12-17T06:23:23.624Z"},{"key":"datr","value":"1UAXXCZB_It3PupVl-oX5fwL","domain":"facebook.com","path":"/","hostOnly":false,"creation":"2018-12-17T06:23:18.108Z","lastAccessed":"2018-12-17T06:23:23.624Z"},{"key":"c_user","value":"100024954724825","expires":"2019-03-17T06:23:18.000Z","maxAge":7776000,"domain":"facebook.com","path":"/","secure":true,"hostOnly":false,"creation":"2018-12-17T06:23:18.824Z","lastAccessed":"2018-12-17T06:23:23.624Z"},{"key":"xs","value":"12%3AREy7ahPzntOnYQ%3A2%3A1545027798%3A14328%3A2627","expires":"2019-03-17T06:23:18.000Z","maxAge":7776000,"domain":"facebook.com","path":"/","secure":true,"httpOnly":true,"hostOnly":false,"creation":"2018-12-17T06:23:18.824Z","lastAccessed":"2018-12-17T06:23:23.624Z"},{"key":"pl","value":"n","expires":"2019-03-17T06:23:18.000Z","maxAge":7776000,"domain":"facebook.com","path":"/","secure":true,"httpOnly":true,"hostOnly":false,"creation":"2018-12-17T06:23:18.824Z","lastAccessed":"2018-12-17T06:23:23.624Z"},{"key":"spin","value":"r.4641669_b.trunk_t.1545027798_s.1_v.2_","expires":"2018-12-18T07:23:18.000Z","maxAge":90000,"domain":"facebook.com","path":"/","secure":true,"httpOnly":true,"hostOnly":false,"creation":"2018-12-17T06:23:18.914Z","lastAccessed":"2018-12-17T06:23:23.624Z"},{"key":"presence","value":"EDvF3EtimeF1545027803EuserFA21B24954724825A2EstateFDutF0Et2F_5b_5dElm2FnullEuct2F1545027803243EtrFnullEtwF710764223EatF1545027803243CEchFDp_5f1B24954724825F0CC","domain":"facebook.com","path":"/","secure":true,"hostOnly":false,"creation":"2018-12-17T06:23:23.244Z","lastAccessed":"2018-12-17T06:23:23.624Z"},{"key":"locale","value":"en_US","domain":"facebook.com","path":"/","secure":true,"hostOnly":false,"creation":"2018-12-17T06:23:23.245Z","lastAccessed":"2018-12-17T06:23:23.624Z"},{"key":"a11y","value":"%7B%22sr%22%3A0%2C%22sr-ts%22%3A1545027803245%2C%22jk%22%3A0%2C%22jk-ts%22%3A1545027803245%2C%22kb%22%3A0%2C%22kb-ts%22%3A1545027803245%2C%22hcm%22%3A0%2C%22hcm-ts%22%3A1545027803245%7D","domain":"facebook.com","path":"/","secure":true,"hostOnly":false,"creation":"2018-12-17T06:23:23.245Z","lastAccessed":"2018-12-17T06:23:23.624Z"},{"key":"fr","value":"1jbew1uFcFx8cDIzO.AWUT6_WikXKh4zJlWxSBRyFwcZk.BcF0DV.Zy.AAA.0.0.BcF0DW.AWW3I3qr","expires":"2019-03-17T06:23:18.000Z","maxAge":7776000,"domain":"messenger.com","path":"/","secure":true,"httpOnly":true,"hostOnly":false,"creation":"2018-12-17T06:23:18.037Z","lastAccessed":"2018-12-17T06:23:23.624Z"},{"key":"sb","value":"1UAXXNo4j8DpHqfowQEyXZ4S","expires":"2020-12-16T06:23:18.000Z","maxAge":63072000,"domain":"messenger.com","path":"/","secure":true,"httpOnly":true,"hostOnly":false,"creation":"2018-12-17T06:23:18.038Z","lastAccessed":"2018-12-17T06:23:23.624Z"},{"key":"c_user","value":"100024954724825","expires":"2019-03-17T06:23:18.000Z","maxAge":7776000,"domain":"messenger.com","path":"/","secure":true,"hostOnly":false,"creation":"2018-12-17T06:23:18.826Z","lastAccessed":"2018-12-17T06:23:23.624Z"},{"key":"xs","value":"12%3AREy7ahPzntOnYQ%3A2%3A1545027798%3A14328%3A2627","expires":"2019-03-17T06:23:18.000Z","maxAge":7776000,"domain":"messenger.com","path":"/","secure":true,"httpOnly":true,"hostOnly":false,"creation":"2018-12-17T06:23:18.826Z","lastAccessed":"2018-12-17T06:23:23.624Z"},{"key":"pl","value":"n","expires":"2019-03-17T06:23:18.000Z","maxAge":7776000,"domain":"messenger.com","path":"/","secure":true,"httpOnly":true,"hostOnly":false,"creation":"2018-12-17T06:23:18.826Z","lastAccessed":"2018-12-17T06:23:23.624Z"},{"key":"spin","value":"r.4641669_b.trunk_t.1545027798_s.1_v.2_","expires":"2018-12-18T07:23:18.000Z","maxAge":90000,"domain":"messenger.com","path":"/","secure":true,"httpOnly":true,"hostOnly":false,"creation":"2018-12-17T06:23:21.156Z","lastAccessed":"2018-12-17T06:23:23.624Z"},{"key":"presence","value":"EDvF3EtimeF1545027803EuserFA21B24954724825A2EstateFDutF0Et2F_5b_5dElm2FnullEuct2F1545027803243EtrFnullEtwF710764223EatF1545027803243CEchFDp_5f1B24954724825F0CC","domain":"messenger.com","path":"/","secure":true,"hostOnly":false,"creation":"2018-12-17T06:23:23.244Z","lastAccessed":"2018-12-17T06:23:23.624Z"},{"key":"locale","value":"en_US","domain":"messenger.com","path":"/","secure":true,"hostOnly":false,"creation":"2018-12-17T06:23:23.245Z","lastAccessed":"2018-12-17T06:23:23.624Z"}]